LICENSE
MANIFEST.in
README.md
setup.py
mendeleystats/__init__.py
mendeleystats/apidefinitions.py
mendeleystats/keys_api.mendeley.com.pkl
mendeleystats/mendeley_client.py
mendeleystats/stats.py
mendeleystats.egg-info/PKG-INFO
mendeleystats.egg-info/SOURCES.txt
mendeleystats.egg-info/dependency_links.txt
mendeleystats.egg-info/not-zip-safe
mendeleystats.egg-info/requires.txt
mendeleystats.egg-info/top_level.txt
scripts/mendeleystats