Metadata-Version: 1.1
Name: mendeleystats
Version: 0.1
Summary: A command line tool to extract information about papers in a Mendeley folder.
Home-page: https://github.com/yurimalheiros/mendeleystats
Author: Yuri Malheiros
Author-email: contato@yurimalheiros.com
License: Copyright © 2013 Yuri Malheiros
